MANIFEST.in
README.md
setup.py
distnet/__init__.py
distnet/__main__.py
distnet.egg-info/PKG-INFO
distnet.egg-info/SOURCES.txt
distnet.egg-info/dependency_links.txt
distnet.egg-info/requires.txt
distnet.egg-info/top_level.txt
distnet/ioctl/__init__.py
distnet/ioctl/io_controller.py
distnet/networking/__init__.py
distnet/networking/network_controller.py
distnet/resources/VERSION
distnet/resources/GeoIP/GeoLite2-Country-Blocks-IPv4.csv
distnet/resources/GeoIP/GeoLite2-Country-Locations-en.csv
distnet/resources/GeoIP/LICENSE.txt
distnet/resources/GeoIP/README.txt
distnet/tcp/__init__.py
distnet/tcp/tcp_file_entry.py
distnet/tcp/tcp_file_handler.py
distnet/tcp/tcp_structs.py
distnet/tcp/tcp_structs_exceptions.py
distnet/utils/__init__.py
distnet/utils/game_controller.py
distnet/utils/hex_manip.py
distnet/utils/mm_geoip_interpreter.py
distnet/utils/os_check.py