Metadata-Version: 2.1
Name: distnet
Version: 0.1.703
Summary: TCP connections visualizer.
Home-page: https://github.com/p0licat/distnet
Author: p0licat
Author-email: tbodica@gmail.com
License: LICENSE.txt
Platform: UNKNOWN
Classifier: Programming Language :: Python :: 3
Classifier: License :: OSI Approved :: GNU Lesser General Public License v3 or later (LGPLv3+)
Classifier: Operating System :: POSIX :: Linux
